circuit.v
`timescale 1ns / 1ps
`include "iob_lib.vh"

module circuit
  #(
    parameter W=32
    )
  (
   `INPUT(rst,1),
   `INPUT(clk,1),
   `INPUT(en,1),
   `INPUT(x,W),
   `OUTPUT(y,W)
   );

   `SIGNAL(cnt, 7) //7-bit counter as iterator
   
   `SIGNAL(y_int, W) //internal y
   `SIGNAL(x_int, W) //internal x

   `SIGNAL(y_int_n_1, W) //y(n-1)
   `SIGNAL2OUT(y, y_int) //connect internal y to output

   //y shift register 
   `REG_ARE(clk, rst, 1'b0, cnt!=99, y_int_n_1, y_int)

   //iteration counter
   `COUNTER_ARE(clk, rst, cnt!=99, cnt)

   //compute next why
   `COMB y_int = 2* y_int_n_1 + x;
   
   
endmodule

circuit_tb.v
`timescale 1ns / 1ps
`include "iob_lib.vh"

`define W 96

module circuit_tb;

   `CLOCK(clk, 10)
   `RESET(rst, 1, 10)
   `SIGNAL(en, 1)
   `SIGNAL_OUT(y, `W)
   `SIGNAL(x, `W)

   integer i;
   
   initial begin
      $dumpfile("circuit.vcd");
      $dumpvars();
      en=0;
      for (i=0; i<100; i=i+1) begin
         @(posedge clk) #1 en=1;$display("%d: %d",i+1, y);
         @(posedge clk) #1 x = $random ;$display("%d:", x);
	
      end

      @(posedge clk) #100 $finish;

   end 

   circuit
     #(
       .W(`W)
       ) 
   c0
     (
      .rst(rst),
      .clk(clk),
      .en(en),
      .x(x),
      .y(y)
      );


endmodule

circuit.vcd
$date
	Tue Nov 17 23:00:51 2020
$end
$version
	Icarus Verilog
$end
$timescale
	1ps
$end
$scope module circuit_tb $end
$var wire 96 ! y [95:0] $end
$var reg 1 " clk $end
$var reg 1 # en $end
$var reg 1 $ rst $end
$var reg 96 % x [95:0] $end
$var integer 32 & i [31:0] $end
$scope module c0 $end
$var wire 1 " clk $end
$var wire 1 # en $end
$var wire 1 $ rst $end
$var wire 96 ' x [95:0] $end
$var wire 96 ( y [95:0] $end
$var reg 7 ) cnt [6:0] $end
$var reg 96 * y_int [95:0] $end
$var reg 96 + y_int_n_1 [95:0] $end
$upscope $end
$upscope $end
$enddefinitions $end
#0
$dumpvars
bx +
bx *
bx )
bx (
bx '
b0 &
bx %
0$
0#
1"
bx !
$end
#1000
b0 )
b0 +
1$
#5000
0"
#10000
1"
#11000
1#
0$
#15000
0"
#20000
b1 )
bx +
1"
#21000
b1 &
b10010000101010011010100100100 %
b10010000101010011010100100100 '
#25000
0"
#30000
b10 )
1"
#35000
0"
#40000
b11 )
1"
#41000
b10 &
b111111111111111111111111111111111111111111111111111111111111111111000000100010010101111010000001 %
b111111111111111111111111111111111111111111111111111111111111111111000000100010010101111010000001 '
#45000
0"
#50000
b100 )
1"
#55000
0"
#60000
b101 )
1"
#61000
b11 &
b111111111111111111111111111111111111111111111111111111111111111110000100100001001101011000001001 %
b111111111111111111111111111111111111111111111111111111111111111110000100100001001101011000001001 '
#65000
0"
#70000
b110 )
1"
#75000
0"
#80000
b111 )
1"
#81000
b100 &
b111111111111111111111111111111111111111111111111111111111111111110110001111100000101011001100011 %
b111111111111111111111111111111111111111111111111111111111111111110110001111100000101011001100011 '
#85000
0"
#90000
b1000 )
1"
#95000
0"
#100000
b1001 )
1"
#101000
b101 &
b110101110010111101100001101 %
b110101110010111101100001101 '
#105000
0"
#110000
b1010 )
1"
#115000
0"
#120000
b1011 )
1"
#121000
b110 &
b1000110110111111001100110001101 %
b1000110110111111001100110001101 '
#125000
0"
#130000
b1100 )
1"
#135000
0"
#140000
b1101 )
1"
#141000
b111 &
b111111111111111111111111111111111111111111111111111111111111111110110010110000101000010001100101 %
b111111111111111111111111111111111111111111111111111111111111111110110010110000101000010001100101 '
#145000
0"
#150000
b1110 )
1"
#155000
0"
#160000
b1111 )
1"
#161000
b1000 &
b111111111111111111111111111111111111111111111111111111111111111110001001001101110101001000010010 %
b111111111111111111111111111111111111111111111111111111111111111110001001001101110101001000010010 '
#165000
0"
#170000
b10000 )
1"
#175000
0"
#180000
b10001 )
1"
#181000
b1001 &
b111100111110001100000001 %
b111100111110001100000001 '
#185000
0"
#190000
b10010 )
1"
#195000
0"
#200000
b10011 )
1"
#201000
b1010 &
b110110101111100110100001101 %
b110110101111100110100001101 '
#205000
0"
#210000
b10100 )
1"
#215000
0"
#220000
b10101 )
1"
#221000
b1011 &
b111011001000111111000101110110 %
b111011001000111111000101110110 '
#225000
0"
#230000
b10110 )
1"
#235000
0"
#240000
b10111 )
1"
#241000
b1100 &
b11110100011011100110100111101 %
b11110100011011100110100111101 '
#245000
0"
#250000
b11000 )
1"
#255000
0"
#260000
b11001 )
1"
#261000
b1101 &
b1110110110101000101011111101101 %
b1110110110101000101011111101101 '
#265000
0"
#270000
b11010 )
1"
#275000
0"
#280000
b11011 )
1"
#281000
b1110 &
b1000110001011011111011110001100 %
b1000110001011011111011110001100 '
#285000
0"
#290000
b11100 )
1"
#295000
0"
#300000
b11101 )
1"
#301000
b1111 &
b1111100111111011110100111111001 %
b1111100111111011110100111111001 '
#305000
0"
#310000
b11110 )
1"
#315000
0"
#320000
b11111 )
1"
#321000
b10000 &
b111111111111111111111111111111111111111111111111111111111111111111100011001101110010010011000110 %
b111111111111111111111111111111111111111111111111111111111111111111100011001101110010010011000110 '
#325000
0"
#330000
b100000 )
1"
#335000
0"
#340000
b100001 )
1"
#341000
b10001 &
b111111111111111111111111111111111111111111111111111111111111111111100010111101111000010011000101 %
b111111111111111111111111111111111111111111111111111111111111111111100010111101111000010011000101 '
#345000
0"
#350000
b100010 )
1"
#355000
0"
#360000
b100011 )
1"
#361000
b10010 &
b111111111111111111111111111111111111111111111111111111111111111111010101000100111101001010101010 %
b111111111111111111111111111111111111111111111111111111111111111111010101000100111101001010101010 '
#365000
0"
#370000
b100100 )
1"
#375000
0"
#380000
b100101 )
1"
#381000
b10011 &
b1110010101011111111011111100101 %
b1110010101011111111011111100101 '
#385000
0"
#390000
b100110 )
1"
#395000
0"
#400000
b100111 )
1"
#401000
b10100 &
b111111111111111111111111111111111111111111111111111111111111111110111011110100100111001001110111 %
b111111111111111111111111111111111111111111111111111111111111111110111011110100100111001001110111 '
#405000
0"
#410000
b101000 )
1"
#415000
0"
#420000
b101001 )
1"
#421000
b10101 &
b111111111111111111111111111111111111111111111111111111111111111110001001001100101101011000010010 %
b111111111111111111111111111111111111111111111111111111111111111110001001001100101101011000010010 '
#425000
0"
#430000
b101010 )
1"
#435000
0"
#440000
b101011 )
1"
#441000
b10110 &
b1000111111011001101101110001111 %
b1000111111011001101101110001111 '
#445000
0"
#450000
b101100 )
1"
#455000
0"
#460000
b101101 )
1"
#461000
b10111 &
b1111001001100000110100111110010 %
b1111001001100000110100111110010 '
#465000
0"
#470000
b101110 )
1"
#475000
0"
#480000
b101111 )
1"
#481000
b11000 &
b111111111111111111111111111111111111111111111111111111111111111111100111011101101001011011001110 %
b111111111111111111111111111111111111111111111111111111111111111111100111011101101001011011001110 '
#485000
0"
#490000
b110000 )
1"
#495000
0"
#500000
b110001 )
1"
#501000
b11001 &
b111111111111111111111111111111111111111111111111111111111111111111110100000000000111101011101000 %
b111111111111111111111111111111111111111111111111111111111111111111110100000000000111101011101000 '
#505000
0"
#510000
b110010 )
1"
#515000
0"
#520000
b110011 )
1"
#521000
b11010 &
b111111111111111111111111111111111111111111111111111111111111111111100010110010100100111011000101 %
b111111111111111111111111111111111111111111111111111111111111111111100010110010100100111011000101 '
#525000
0"
#530000
b110100 )
1"
#535000
0"
#540000
b110101 )
1"
#541000
b11011 &
b101110010110000100100101011100 %
b101110010110000100100101011100 '
#545000
0"
#550000
b110110 )
1"
#555000
0"
#560000
b110111 )
1"
#561000
b11100 &
b111111111111111111111111111111111111111111111111111111111111111111011110100011100010100010111101 %
b111111111111111111111111111111111111111111111111111111111111111111011110100011100010100010111101 '
#565000
0"
#570000
b111000 )
1"
#575000
0"
#580000
b111001 )
1"
#581000
b11101 &
b111111111111111111111111111111111111111111111111111111111111111110010110101010110101100000101101 %
b111111111111111111111111111111111111111111111111111111111111111110010110101010110101100000101101 '
#585000
0"
#590000
b111010 )
1"
#595000
0"
#600000
b111011 )
1"
#601000
b11110 &
b111111111111111111111111111111111111111111111111111111111111111110110010101001110010011001100101 %
b111111111111111111111111111111111111111111111111111111111111111110110010101001110010011001100101 '
#605000
0"
#610000
b111100 )
1"
#615000
0"
#620000
b111101 )
1"
#621000
b11111 &
b111111111111111111111111111111111111111111111111111111111111111110110001111011110110001001100011 %
b111111111111111111111111111111111111111111111111111111111111111110110001111011110110001001100011 '
#625000
0"
#630000
b111110 )
1"
#635000
0"
#640000
b111111 )
1"
#641000
b100000 &
b101011100111000011100001010 %
b101011100111000011100001010 '
#645000
0"
#650000
b1000000 )
1"
#655000
0"
#660000
b1000001 )
1"
#661000
b100001 &
b111111111111111111111111111111111111111111111111111111111111111111000000001110110010001010000000 %
b111111111111111111111111111111111111111111111111111111111111111111000000001110110010001010000000 '
#665000
0"
#670000
b1000010 )
1"
#675000
0"
#680000
b1000011 )
1"
#681000
b100010 &
b10000011001000010000100100000 %
b10000011001000010000100100000 '
#685000
0"
#690000
b1000100 )
1"
#695000
0"
#700000
b1000101 )
1"
#701000
b100011 &
b1010101011110000100010110101010 %
b1010101011110000100010110101010 '
#705000
0"
#710000
b1000110 )
1"
#715000
0"
#720000
b1000111 )
1"
#721000
b100100 &
b111111111111111111111111111111111111111111111111111111111111111111001110110011001100110010011101 %
b111111111111111111111111111111111111111111111111111111111111111111001110110011001100110010011101 '
#725000
0"
#730000
b1001000 )
1"
#735000
0"
#740000
b1001001 )
1"
#741000
b100101 &
b111111111111111111111111111111111111111111111111111111111111111111001011001000000011111010010110 %
b111111111111111111111111111111111111111111111111111111111111111111001011001000000011111010010110 '
#745000
0"
#750000
b1001010 )
1"
#755000
0"
#760000
b1001011 )
1"
#761000
b100110 &
b111111111111111111111111111111111111111111111111111111111111111110001001100000111011100000010011 %
b111111111111111111111111111111111111111111111111111111111111111110001001100000111011100000010011 '
#765000
0"
#770000
b1001100 )
1"
#775000
0"
#780000
b1001101 )
1"
#781000
b100111 &
b111111111111111111111111111111111111111111111111111111111111111110000110101111000011100000001101 %
b111111111111111111111111111111111111111111111111111111111111111110000110101111000011100000001101 '
#785000
0"
#790000
b1001110 )
1"
#795000
0"
#800000
b1001111 )
1"
#801000
b101000 &
b111111111111111111111111111111111111111111111111111111111111111110101001101001111101011001010011 %
b111111111111111111111111111111111111111111111111111111111111111110101001101001111101011001010011 '
#805000
0"
#810000
b1010000 )
1"
#815000
0"
#820000
b1010001 )
1"
#821000
b101001 &
b110101100111111101110101101011 %
b110101100111111101110101101011 '
#825000
0"
#830000
b1010010 )
1"
#835000
0"
#840000
b1010011 )
1"
#841000
b101010 &
b111111111111111111111111111111111111111111111111111111111111111111101010101001100010101011010101 %
b111111111111111111111111111111111111111111111111111111111111111111101010101001100010101011010101 '
#845000
0"
#850000
b1010100 )
1"
#855000
0"
#860000
b1010101 )
1"
#861000
b101011 &
b111111111111111111111111111111111111111111111111111111111111111110000001000101110100101000000010 %
b111111111111111111111111111111111111111111111111111111111111111110000001000101110100101000000010 '
#865000
0"
#870000
b1010110 )
1"
#875000
0"
#880000
b1010111 )
1"
#881000
b101100 &
b111111111111111111111111111111111111111111111111111111111111111111010111010101100011111010101110 %
b111111111111111111111111111111111111111111111111111111111111111111010111010101100011111010101110 '
#885000
0"
#890000
b1011000 )
1"
#895000
0"
#900000
b1011001 )
1"
#901000
b101101 &
b1110111111111110100100011101 %
b1110111111111110100100011101 '
#905000
0"
#910000
b1011010 )
1"
#915000
0"
#920000
b1011011 )
1"
#921000
b101110 &
b111111111111111111111111111111111111111111111111111111111111111111100111110001010111001011001111 %
b111111111111111111111111111111111111111111111111111111111111111111100111110001010111001011001111 '
#925000
0"
#930000
b1011100 )
1"
#935000
0"
#940000
b1011101 )
1"
#941000
b101111 &
b10001100001000100100100100011 %
b10001100001000100100100100011 '
#945000
0"
#950000
b1011110 )
1"
#955000
0"
#960000
b1011111 )
1"
#961000
b110000 &
b101000010010110010100001010 %
b101000010010110010100001010 '
#965000
0"
#970000
b1100000 )
1"
#975000
0"
#980000
b1100001 )
1"
#981000
b110001 &
b111111111111111111111111111111111111111111111111111111111111111111100101011100110000101011001010 %
b111111111111111111111111111111111111111111111111111111111111111111100101011100110000101011001010 '
#985000
0"
#990000
b1100010 )
1"
#995000
0"
#1000000
b1100011 )
1"
#1001000
b110010 &
b111111111111111111111111111111111111111111111111111111111111111110011110001100010100110000111100 %
b111111111111111111111111111111111111111111111111111111111111111110011110001100010100110000111100 '
#1005000
0"
#1010000
1"
#1015000
0"
#1020000
1"
#1021000
b110011 &
b1111001011010001011110111110010 %
b1111001011010001011110111110010 '
#1025000
0"
#1030000
1"
#1035000
0"
#1040000
1"
#1041000
b110100 &
b1000101001011100110000110001010 %
b1000101001011100110000110001010 '
#1045000
0"
#1050000
1"
#1055000
0"
#1060000
1"
#1061000
b110101 &
b100000110001001011001101000001 %
b100000110001001011001101000001 '
#1065000
0"
#1070000
1"
#1075000
0"
#1080000
1"
#1081000
b110110 &
b111111111111111111111111111111111111111111111111111111111111111111101100010010110011010011011000 %
b111111111111111111111111111111111111111111111111111111111111111111101100010010110011010011011000 '
#1085000
0"
#1090000
1"
#1095000
0"
#1100000
1"
#1101000
b110111 &
b111100001000001111001101111000 %
b111100001000001111001101111000 '
#1105000
0"
#1110000
1"
#1115000
0"
#1120000
1"
#1121000
b111000 &
b111111111111111111111111111111111111111111111111111111111111111111000100100010100001001010001001 %
b111111111111111111111111111111111111111111111111111111111111111111000100100010100001001010001001 '
#1125000
0"
#1130000
1"
#1135000
0"
#1140000
1"
#1141000
b111001 &
b1110101110001010000110111101011 %
b1110101110001010000110111101011 '
#1145000
0"
#1150000
1"
#1155000
0"
#1160000
1"
#1161000
b111010 &
b1011011000000100110010110110110 %
b1011011000000100110010110110110 '
#1165000
0"
#1170000
1"
#1175000
0"
#1180000
1"
#1181000
b111011 &
b1100011010010111111100111000110 %
b1100011010010111111100111000110 '
#1185000
0"
#1190000
1"
#1195000
0"
#1200000
1"
#1201000
b111100 &
b1010111000101010001001110101110 %
b1010111000101010001001110101110 '
#1205000
0"
#1210000
1"
#1215000
0"
#1220000
1"
#1221000
b111101 &
b111111111111111111111111111111111111111111111111111111111111111111011110011101010000001010111100 %
b111111111111111111111111111111111111111111111111111111111111111111011110011101010000001010111100 '
#1225000
0"
#1230000
1"
#1235000
0"
#1240000
1"
#1241000
b111110 &
b10101000011111101110100101010 %
b10101000011111101110100101010 '
#1245000
0"
#1250000
1"
#1255000
0"
#1260000
1"
#1261000
b111111 &
b111111111111111111111111111111111111111111111111111111111111111110000101110101111001101000001011 %
b111111111111111111111111111111111111111111111111111111111111111110000101110101111001101000001011 '
#1265000
0"
#1270000
1"
#1275000
0"
#1280000
1"
#1281000
b1000000 &
b111111111111111111111111111111111111111111111111111111111111111110111000100101111011111001110001 %
b111111111111111111111111111111111111111111111111111111111111111110111000100101111011111001110001 '
#1285000
0"
#1290000
1"
#1295000
0"
#1300000
1"
#1301000
b1000001 &
b1000010111100100100000110000101 %
b1000010111100100100000110000101 '
#1305000
0"
#1310000
1"
#1315000
0"
#1320000
1"
#1321000
b1000010 &
b100111111100100101010101001111 %
b100111111100100101010101001111 '
#1325000
0"
#1330000
1"
#1335000
0"
#1340000
1"
#1341000
b1000011 &
b111111111111111111111111111111111111111111111111111111111111111110011101110011000110000000111011 %
b111111111111111111111111111111111111111111111111111111111111111110011101110011000110000000111011 '
#1345000
0"
#1350000
1"
#1355000
0"
#1360000
1"
#1361000
b1000100 &
b11101000001100011001100111010 %
b11101000001100011001100111010 '
#1365000
0"
#1370000
1"
#1375000
0"
#1380000
1"
#1381000
b1000101 &
b111111111111111111111111111111111111111111111111111111111111111110111111001000110011001001111110 %
b111111111111111111111111111111111111111111111111111111111111111110111111001000110011001001111110 '
#1385000
0"
#1390000
1"
#1395000
0"
#1400000
1"
#1401000
b1000110 &
b1010101010100100101100010101 %
b1010101010100100101100010101 '
#1405000
0"
#1410000
1"
#1415000
0"
#1420000
1"
#1421000
b1000111 &
b1111000110110011001101111110001 %
b1111000110110011001101111110001 '
#1425000
0"
#1430000
1"
#1435000
0"
#1440000
1"
#1441000
b1001000 &
b1101100100111000100101111011001 %
b1101100100111000100101111011001 '
#1445000
0"
#1450000
1"
#1455000
0"
#1460000
1"
#1461000
b1001001 &
b110001001000110000011101100010 %
b110001001000110000011101100010 '
#1465000
0"
#1470000
1"
#1475000
0"
#1480000
1"
#1481000
b1001010 &
b100110001101011111101101001100 %
b100110001101011111101101001100 '
#1485000
0"
#1490000
1"
#1495000
0"
#1500000
1"
#1501000
b1001011 &
b1001111101000010101010110011111 %
b1001111101000010101010110011111 '
#1505000
0"
#1510000
1"
#1515000
0"
#1520000
1"
#1521000
b1001100 &
b1000111101110011010000110001111 %
b1000111101110011010000110001111 '
#1525000
0"
#1530000
1"
#1535000
0"
#1540000
1"
#1541000
b1001101 &
b1111100011011011010100111111000 %
b1111100011011011010100111111000 '
#1545000
0"
#1550000
1"
#1555000
0"
#1560000
1"
#1561000
b1001110 &
b111111111111111111111111111111111111111111111111111111111111111111011011110011010110000010110111 %
b111111111111111111111111111111111111111111111111111111111111111111011011110011010110000010110111 '
#1565000
0"
#1570000
1"
#1575000
0"
#1580000
1"
#1581000
b1001111 &
b111111111111111111111111111111111111111111111111111111111111111111001111110001000101011010011111 %
b111111111111111111111111111111111111111111111111111111111111111111001111110001000101011010011111 '
#1585000
0"
#1590000
1"
#1595000
0"
#1600000
1"
#1601000
b1010000 &
b111111111111111111111111111111111111111111111111111111111111111110101110011111011001010001011100 %
b111111111111111111111111111111111111111111111111111111111111111110101110011111011001010001011100 '
#1605000
0"
#1610000
1"
#1615000
0"
#1620000
1"
#1621000
b1010001 &
b111111111111111111111111111111111111111111111111111111111111111110101101110010111100000001011011 %
b111111111111111111111111111111111111111111111111111111111111111110101101110010111100000001011011 '
#1625000
0"
#1630000
1"
#1635000
0"
#1640000
1"
#1641000
b1010010 &
b1000100110111100011011110001001 %
b1000100110111100011011110001001 '
#1645000
0"
#1650000
1"
#1655000
0"
#1660000
1"
#1661000
b1010011 &
b111111111111111111111111111111111111111111111111111111111111111110100100101011100011001001001001 %
b111111111111111111111111111111111111111111111111111111111111111110100100101011100011001001001001 '
#1665000
0"
#1670000
1"
#1675000
0"
#1680000
1"
#1681000
b1010100 &
b111111111111111111111111111111111111111111111111111111111111111111101000001000110011111011010000 %
b111111111111111111111111111111111111111111111111111111111111111111101000001000110011111011010000 '
#1685000
0"
#1690000
1"
#1695000
0"
#1700000
1"
#1701000
b1010101 &
b111111111111111111111111111111111111111111111111111111111111111111101011111111101100000011010111 %
b111111111111111111111111111111111111111111111111111111111111111111101011111111101100000011010111 '
#1705000
0"
#1710000
1"
#1715000
0"
#1720000
1"
#1721000
b1010110 &
b111111111111111111111111111111111111111111111111111111111111111110101000110001111111110001010001 %
b111111111111111111111111111111111111111111111111111111111111111110101000110001111111110001010001 '
#1725000
0"
#1730000
1"
#1735000
0"
#1740000
1"
#1741000
b1010111 &
b1001011001000010010111110010110 %
b1001011001000010010111110010110 '
#1745000
0"
#1750000
1"
#1755000
0"
#1760000
1"
#1761000
b1011000 &
b110000111010111111100001100 %
b110000111010111111100001100 '
#1765000
0"
#1770000
1"
#1775000
0"
#1780000
1"
#1781000
b1011001 &
b111111111111111111111111111111111111111111111111111111111111111111100001001011001100111011000010 %
b111111111111111111111111111111111111111111111111111111111111111111100001001011001100111011000010 '
#1785000
0"
#1790000
1"
#1795000
0"
#1800000
1"
#1801000
b1011010 &
b1100100010101111110110111001000 %
b1100100010101111110110111001000 '
#1805000
0"
#1810000
1"
#1815000
0"
#1820000
1"
#1821000
b1011011 &
b111111111111111111111111111111111111111111111111111111111111111110111011100000100101101001110111 %
b111111111111111111111111111111111111111111111111111111111111111110111011100000100101101001110111 '
#1825000
0"
#1830000
1"
#1835000
0"
#1840000
1"
#1841000
b1011100 &
b11110111100101110110100111101 %
b11110111100101110110100111101 '
#1845000
0"
#1850000
1"
#1855000
0"
#1860000
1"
#1861000
b1011101 &
b1001000011001101101100010010 %
b1001000011001101101100010010 '
#1865000
0"
#1870000
1"
#1875000
0"
#1880000
1"
#1881000
b1011110 &
b111111111111111111111111111111111111111111111111111111111111111110111111000001010000000001111110 %
b111111111111111111111111111111111111111111111111111111111111111110111111000001010000000001111110 '
#1885000
0"
#1890000
1"
#1895000
0"
#1900000
1"
#1901000
b1011111 &
b110110111001011000000101101101 %
b110110111001011000000101101101 '
#1905000
0"
#1910000
1"
#1915000
0"
#1920000
1"
#1921000
b1100000 &
b11100110110011110011100111001 %
b11100110110011110011100111001 '
#1925000
0"
#1930000
1"
#1935000
0"
#1940000
1"
#1941000
b1100001 &
b1111110100101000111100011111 %
b1111110100101000111100011111 '
#1945000
0"
#1950000
1"
#1955000
0"
#1960000
1"
#1961000
b1100010 &
b111111111111111111111111111111111111111111111111111111111111111111101001111010111111011011010011 %
b111111111111111111111111111111111111111111111111111111111111111111101001111010111111011011010011 '
#1965000
0"
#1970000
1"
#1975000
0"
#1980000
1"
#1981000
b1100011 &
b1000010110110010010111110000101 %
b1000010110110010010111110000101 '
#1985000
0"
#1990000
1"
#1995000
0"
#2000000
1"
#2001000
b1100100 &
b111111111111111111111111111111111111111111111111111111111111111110111100000101001000100001111000 %
b111111111111111111111111111111111111111111111111111111111111111110111100000101001000100001111000 '
